{
     "pair": {
        "pair_1": {
            "src": "508.jpg",
            "dst": "320.jpg"
        },
        "pair_2": {
            "src": "525.jpg",
            "dst": "320.jpg"
        },
        "pair_3": {
            "src": "572.jpg",
            "dst": "19.jpg"
        },
        "pair_4": {
            "src": "320.jpg",
            "dst": "19.jpg"
        }
     },

    "pairwise": {
        "src": [
            "60065.jpg", 
            "60028.jpg"
        ],

        "dst": [
            "60949.jpg", 
            "60812.jpg"
        ]
    }
 }