 {
    "log=Face_woclip_cfg=Face_woclip.yaml" :  {
        "step":"ema_050000", 
        "itp":"render_face_modSH", 
        "alias":"Deca + Arcface : Enc(Rendered Face) (128x128)"
    },
    "log=Masked_Face_woclip_no_nonspatial_cfg=Masked_Face_woclip_no_nonspatial.yaml" :  {
        "step":"ema_050000", 
        "itp":"render_face_modSH", 
        "alias":"No-nonspatial : Enc(Rendered Face) (128x128)"
    },
    "log=Masked_Face_woclip_no_nonspatial_cfg=Masked_Face_woclip_no_nonspatial.yaml_separate_reverse" :  {
        "step":"ema_050000", 
        "itp":"render_face_modSH", 
        "alias":"No-nonspatial (Separate Reverse) : Enc(Rendered Face) (128x128)"
    },
    "log=Masked_Face_woclip_Arcface_cfg=Masked_Face_woclip_Arcface.yaml" :  {
        "step":"ema_050000", 
        "itp":"render_face_modSH", 
        "alias":"Only Arcface : Enc(Rendered Face) (128x128)"
    },
    "log=Masked_Face_woclip_Deca_cfg=Masked_Face_woclip_Deca.yaml" :  {
        "step":"ema_050000", 
        "itp":"render_face_modSH", 
        "alias":"Only Deca : Enc(Rendered Face) (128x128)"
    }
}
